multiprocessing_logging.py
tests/__init__.py
tests/test_multiprocessing_logging.py
multiprocessing_logging-0.3.2.dist-info/LICENSE
multiprocessing_logging-0.3.2.dist-info/METADATA
multiprocessing_logging-0.3.2.dist-info/WHEEL
multiprocessing_logging-0.3.2.dist-info/top_level.txt
multiprocessing_logging-0.3.2.dist-info/RECORD
