Metadata-Version: 2.1
Name: multiprocessing-logging
Version: 0.3.2
Summary: Logger for multiprocessing applications
Home-page: https://github.com/jruere/multiprocessing-logging
Author: Javier Ruere
Author-email: javier@ruere.com.ar
License: LGPLv3
Keywords: multiprocessing logging logger handler
Platform: POSIX
Classifier: Development Status :: 5 - Production/Stable
Classifier: Intended Audience :: Developers
Classifier: License :: OSI Approved :: GNU Lesser General Public License v3 or later (LGPLv3+)
Classifier: Programming Language :: Python :: 3
Classifier: Programming Language :: Python :: 3.6
Classifier: Programming Language :: Python :: 3.7
Classifier: Programming Language :: Python :: 3.8
Classifier: Programming Language :: Python :: 3.9
Classifier: Programming Language :: Python :: 3.10
Classifier: Programming Language :: Python :: 2
Classifier: Programming Language :: Python :: 2.7
Classifier: Programming Language :: Python :: Implementation :: CPython
Classifier: Operating System :: POSIX
Classifier: Topic :: Software Development :: Libraries :: Python Modules
License-File: LICENSE
